limina_client/__init__.py
limina_client-0.0.1.dist-info/METADATA
limina_client-0.0.1.dist-info/WHEEL
limina_client-0.0.1.dist-info/licenses/LICENSE
limina_client-0.0.1.dist-info/RECORD
