Metadata-Version: 2.4
Name: limina_client
Version: 0.0.1
Summary: A client for communicating with the Limina de-identication API.
Project-URL: Homepage, https://github.com/limina/limina-client/
Author-email: Adam Guiducci <adam.guiducci@private-ai.com>, Bryan Bell-Smith <bryan.bellsmith@private-ai.com>
License-File: LICENSE
Classifier: License :: OSI Approved :: MIT License
Classifier: Operating System :: OS Independent
Classifier: Programming Language :: Python :: 3
Requires-Python: >=3.8
Requires-Dist: pyxdameraulevenshtein~=1.8.0
Requires-Dist: requests~=2.32.3
